chide/__init__.py
chide/collection.py
chide/factory.py
chide/formats.py
chide/py.typed
chide/set.py
chide/simplifiers.py
chide/sqlalchemy.py
chide/typing.py
chide-3.1.0.dist-info/LICENSE.txt
chide-3.1.0.dist-info/METADATA
chide-3.1.0.dist-info/WHEEL
chide-3.1.0.dist-info/top_level.txt
chide-3.1.0.dist-info/RECORD
