Metadata-Version: 2.2
Name: chide
Version: 3.1.0
Summary: Quickly create sample objects from data.
Home-page: https://github.com/cjw296/chide
Author: Chris Withers
Author-email: chris@withers.org
License: MIT
Classifier: Development Status :: 5 - Production/Stable
Classifier: Intended Audience :: Developers
Classifier: License :: OSI Approved :: MIT License
Classifier: Programming Language :: Python :: 3
Requires-Python: >=3.11
License-File: LICENSE.txt
Provides-Extra: test
Requires-Dist: mypy; extra == "test"
Requires-Dist: pytest; extra == "test"
Requires-Dist: pytest-cov; extra == "test"
Requires-Dist: sybil; extra == "test"
Requires-Dist: testfixtures; extra == "test"
Requires-Dist: sqlalchemy; extra == "test"
Provides-Extra: docs
Requires-Dist: furo; extra == "docs"
Requires-Dist: sphinx; extra == "docs"
Requires-Dist: sqlalchemy; extra == "docs"
Provides-Extra: release
Requires-Dist: twine; extra == "release"
Requires-Dist: wheel; extra == "release"
Dynamic: author
Dynamic: author-email
Dynamic: classifier
Dynamic: description
Dynamic: home-page
Dynamic: license
Dynamic: provides-extra
Dynamic: requires-python
Dynamic: summary
